python_spinning_loader/__init__.py
python_spinning_loader/python_loader_cpp.cpython-310-darwin.so
python_spinning_loader/python_loader_cpp.cpython-311-darwin.so
python_spinning_loader/python_loader_cpp.cpython-312-darwin.so
python_spinning_loader/python_loader_cpp.cpython-38-darwin.so
python_spinning_loader/python_loader_cpp.cpython-39-darwin.so
python_spinning_loader-0.1.4.dist-info/METADATA
python_spinning_loader-0.1.4.dist-info/WHEEL
python_spinning_loader-0.1.4.dist-info/top_level.txt
python_spinning_loader-0.1.4.dist-info/RECORD
