Metadata-Version: 2.1
Name: python-spinning-loader
Version: 0.1.4
Summary: A python package that gives access to a spinning loader with a hidden game inside
Author: Van Wynendaele Vincent
Classifier: Programming Language :: Python :: 3
Classifier: License :: OSI Approved :: MIT License
Classifier: Operating System :: OS Independent
Requires-Python: >=3.8
